nr/python/environment/__init__.py
nr/python/environment/distributions.py
nr/python/environment/py.typed
nr/python/environment/utils.py
nr/python/environment/virtualenv.py
nr.python.environment-0.1.4.dist-info/LICENSE
nr.python.environment-0.1.4.dist-info/WHEEL
nr.python.environment-0.1.4.dist-info/METADATA
nr.python.environment-0.1.4.dist-info/RECORD
